px/__init__.py
px/__main__.py
px/config.py
px/debug.py
px/handler.py
px/help.py
px/main.py
px/pac.py
px/pacutils.py
px/version.py
px/windows.py
px/wproxy.py
px_proxy-0.10.1.dist-info/LICENSE.txt
px_proxy-0.10.1.dist-info/METADATA
px_proxy-0.10.1.dist-info/WHEEL
px_proxy-0.10.1.dist-info/entry_points.txt
px_proxy-0.10.1.dist-info/top_level.txt
px_proxy-0.10.1.dist-info/RECORD
