Metadata-Version: 2.2
Name: px-proxy
Version: 0.10.1
Summary: An HTTP proxy server to automatically authenticate through an NTLM proxy
Author-email: Ganesh Viswanathan <dev@genotrance.com>
Project-URL: Homepage, https://github.com/genotrance/px
Project-URL: Repository, https://github.com/genotrance/px
Project-URL: Issues, https://github.com/genotrance/px/issues
Classifier: Development Status :: 4 - Beta
Classifier: Environment :: Win32 (MS Windows)
Classifier: Environment :: MacOS X
Classifier: Intended Audience :: Developers
Classifier: Intended Audience :: End Users/Desktop
Classifier: Intended Audience :: System Administrators
Classifier: License :: OSI Approved :: MIT License
Classifier: Natural Language :: English
Classifier: Operating System :: MacOS :: MacOS X
Classifier: Operating System :: Microsoft :: Windows
Classifier: Operating System :: POSIX :: Linux
Classifier: Programming Language :: Python :: 3.8
Classifier: Programming Language :: Python :: 3.9
Classifier: Programming Language :: Python :: 3.10
Classifier: Programming Language :: Python :: 3.11
Classifier: Programming Language :: Python :: 3.12
Classifier: Programming Language :: Python :: 3.13
Classifier: Topic :: Internet :: Proxy Servers
License-File: LICENSE.txt
Requires-Dist: keyring
Requires-Dist: netaddr
Requires-Dist: psutil
Requires-Dist: pymcurl
Requires-Dist: pyspnego
Requires-Dist: python-dotenv
Requires-Dist: quickjs
